kilonovanet/__init__.py
kilonovanet/cvae.py
kilonovanet/kilonovanet.py
kilonovanet/observations.py
kilonovanet-0.1.1.dist-info/LICENSE
kilonovanet-0.1.1.dist-info/METADATA
kilonovanet-0.1.1.dist-info/WHEEL
kilonovanet-0.1.1.dist-info/top_level.txt
kilonovanet-0.1.1.dist-info/RECORD
