Metadata-Version: 2.1
Name: kilonovanet
Version: 0.1.1
Summary: Kilonova surrogate modelling via cVAE
Home-page: UNKNOWN
Author: Kamile Lukosiute
Author-email: lukosiutekamile@gmail.com
License: UNKNOWN
Platform: UNKNOWN
Classifier: Intended Audience :: Science/Research
Classifier: Operating System :: OS Independent
Classifier: Programming Language :: Python :: 3
Classifier: License :: OSI Approved :: MIT License
Classifier: Topic :: Scientific/Engineering :: Astronomy
Requires-Python: >=3.6
License-File: LICENSE
Requires-Dist: numpy
Requires-Dist: torch
Requires-Dist: pyphot
